{
  "nodes": [
    {
      "id": "public_logo_brand",
      "label": "FoodyBoard Logo Asset",
      "file_type": "image",
      "source_file": "project/frontend/public/logo.png",
      "source_location": null,
      "source_url": null,
      "captured_at": null,
      "author": null,
      "contributor": null
    },
    {
      "id": "public_logo_restaurant_analytics",
      "label": "Restaurant Analytics Concept",
      "file_type": "concept",
      "source_file": "project/frontend/public/logo.png",
      "source_location": null,
      "source_url": null,
      "captured_at": null,
      "author": null,
      "contributor": null
    }
  ],
  "edges": [
    {
      "source": "public_logo_brand",
      "target": "public_logo_restaurant_analytics",
      "relation": "conceptually_related_to",
      "confidence": "INFERRED",
      "confidence_score": 0.85,
      "source_file": "project/frontend/public/logo.png",
      "source_location": null,
      "weight": 1.0
    }
  ],
  "hyperedges": [],
  "input_tokens": 0,
  "output_tokens": 0
}
